AdnGAN/Discriminator.py
AdnGAN/Generator.py
AdnGAN/ProGAN.py
AdnGAN/__init__.py
AdnGAN/dataset.py
AdnGAN/tools.py
AdnGAN-0.1.4.dist-info/METADATA
AdnGAN-0.1.4.dist-info/WHEEL
AdnGAN-0.1.4.dist-info/top_level.txt
AdnGAN-0.1.4.dist-info/RECORD
