Metadata-Version: 2.1
Name: AdnGAN
Version: 0.1.4
Summary: AdnGAN is a Generative Adversarial Network (GAN) that generates images from random noise.
Home-page: https://github.com/AdnaneMaj/AdnGAN/tree/main/AdnGAN
Author: Adnane MAJDOUB
Author-email: adnanemajdoub@gmail.com
Classifier: Programming Language :: Python :: 3
Classifier: License :: OSI Approved :: MIT License
Classifier: Operating System :: OS Independent
Requires-Python: >=3.6
Requires-Dist: torch
Requires-Dist: torchvision
Requires-Dist: numpy
Requires-Dist: matplotlib
